[
{
  "numero": "COT-DIA25001918",
  "fecha": "06/05/2025",
  "ruc": "20538347281",
  "nombre": "INVERSIONES DIAMANTE PERU S.A.C.",
  "moneda": "1",
  "totcompra": "209.6",
  "acuenta": "209.6",
  "saldo": "0.0000",
  "tipc": "3.7",
  "obs": "",
  "tipo": "NAC",
  "factura": "",
  "user": "MARTIN",
  "codart": "DBOL9M",
  "descripcion": "BOLO 9\" ROSE DE VIDRIO (CAJA X  24 UND)",
  "cajas": "10",
  "doce": "0",
  "unidad": "0",
  "vunit": "20.96",
  "total": "209.6",
  "cant": "240",
  "undmy": "24",
  "undmn": "1",
  "leymy": "UND",
  "leymn": "UND",
  "lote": "DBOL9VIDRIO-098-24",
  "grat": "1",
  "locked": "No"
},
]