[
{
  "numero": "COT-YH0001972",
  "fecha": "27/06/2025",
  "ruc": "00000000013",
  "nombre": "YOHON MEZA",
  "moneda": "0",
  "totcompra": "1865",
  "acuenta": "1865",
  "saldo": "0.0000",
  "tipc": "3.7",
  "obs": "",
  "tipo": "NAC",
  "factura": "",
  "user": "MARTIN",
  "codart": "J11SUBL-EQUIP",
  "descripcion": "JARRO 11\" EQUIPOS  (CAJA X  4 DOC)",
  "cajas": "2",
  "doce": "0",
  "unidad": "0",
  "vunit": "155.00",
  "total": "310",
  "cant": "96",
  "undmy": "4",
  "undmn": "12",
  "leymy": "DOC",
  "leymn": "UND",
  "lote": "J11SUBL-EQUIP",
  "grat": "1",
  "locked": "No"
},
{
  "codart": "J11SUBL-PERS",
  "descripcion": "JARRO 11\" PERSONAJES  (CAJA X  4 DOC)",
  "cajas": "10",
  "doce": "0",
  "unidad": "0",
  "vunit": "155.50",
  "total": "1555",
  "cant": "480",
  "undmy": "4",
  "undmn": "12",
  "leymy": "DOC",
  "leymn": "UND",
  "lote": "J11SUBL-PERS",
  "grat": "1",
  "locked": "No"
},
]