[
{
  "numero": "COT-RJ03915",
  "fecha": "30/07/2025",
  "ruc": "00000000016",
  "nombre": "ROSA JARRO",
  "moneda": "0",
  "totcompra": "345",
  "acuenta": "345",
  "saldo": "0.0000",
  "tipc": "3.7",
  "obs": "",
  "tipo": "NAC",
  "factura": "",
  "user": "MARTIN",
  "codart": "ZB5824BL",
  "descripcion": "JARRO CHOPP (CAJA X  24 UND)",
  "cajas": "3",
  "doce": "0",
  "unidad": "0",
  "vunit": "115.00",
  "total": "345",
  "cant": "72",
  "undmy": "24",
  "undmn": "1",
  "leymy": "UND",
  "leymn": "UND",
  "lote": "ZB5824BL",
  "grat": "1",
  "locked": "No"
},
]