[
{
  "numero": "COT-DIA25001694",
  "fecha": "22/04/2025",
  "ruc": "20538347281",
  "nombre": "INVERSIONES DIAMANTE PERU S.A.C.",
  "moneda": "1",
  "totcompra": "465",
  "acuenta": "465",
  "saldo": "0.0000",
  "tipc": "3.7",
  "obs": "",
  "tipo": "NAC",
  "factura": "",
  "user": "MARTIN",
  "codart": "YZ09",
  "descripcion": "JARRA DE VIDRIO 1.0L C/TAPA (CAJA X  1 DOC)",
  "cajas": "30",
  "doce": "0",
  "unidad": "0",
  "vunit": "15.50",
  "total": "465",
  "cant": "360",
  "undmy": "1",
  "undmn": "12",
  "leymy": "DOC",
  "leymn": "UND",
  "lote": "YZ09-083-24A",
  "grat": "1",
  "locked": "No"
},
]