[
{
  "numero": "COT-120219",
  "fecha": "23/04/2025",
  "ruc": "00000000048",
  "nombre": "RONGQUIAN",
  "moneda": "0",
  "totcompra": "3840",
  "acuenta": "3840",
  "saldo": "0.0000",
  "tipc": "3.705",
  "obs": "",
  "tipo": "NAC",
  "factura": "",
  "user": "DANTE",
  "codart": "MS-2202",
  "descripcion": "TAPER VIDRIO 1000ML C/DIVISION (CAJA X  24 UND)",
  "cajas": "20",
  "doce": "0",
  "unidad": "0",
  "vunit": "192.00",
  "total": "3840",
  "cant": "480",
  "undmy": "24",
  "undmn": "1",
  "leymy": "UND",
  "leymn": "UND",
  "lote": "MS-2202",
  "grat": "1",
  "locked": "No"
},
]