[
{
  "numero": "FAC-F063-00065616",
  "fecha": "23/09/2025",
  "ruc": "00000000000",
  "nombre": "CLIENTES VARIOS",
  "moneda": "0",
  "totcompra": "",
  "acuenta": "",
  "saldo": "",
  "tipc": "",
  "obs": "",
  "tipo": "",
  "factura": "",
  "user": "",
  "codart": "XC008",
  "descripcion": "PLATO 10\" TENDIDO COLOR GLASEADO (CAJA X  18 UND)",
  "cajas": "22",
  "doce": "0",
  "unidad": "0",
  "vunit": "15.39",
  "total": "338.577",
  "cant": "396",
  "undmy": "18",
  "undmn": "1",
  "leymy": "UND",
  "leymn": "UND",
  "lote": "XC008",
  "grat": "1",
  "locked": "No"
},
{
  "codart": "XC011",
  "descripcion": "PLATO 10.5\" TENDIDO TURQUEZA (CAJA X  18 UND)",
  "cajas": "23",
  "doce": "0",
  "unidad": "0",
  "vunit": "15.39",
  "total": "353.964",
  "cant": "414",
  "undmy": "18",
  "undmn": "1",
  "leymy": "UND",
  "leymn": "UND",
  "lote": "XC011",
  "grat": "1",
  "locked": "No"
},
]