[
{
  "numero": "COT-CP31792",
  "fecha": "09/06/2026",
  "ruc": "00000000020",
  "nombre": "CASA PORCELANA",
  "moneda": "0",
  "totcompra": "70",
  "acuenta": "70",
  "saldo": "0.0000",
  "tipc": "3.43",
  "obs": "",
  "tipo": "NAC",
  "factura": "",
  "user": "MARTIN",
  "codart": "VT-04",
  "descripcion": "LONCHERA (CAJA X  12 UND)",
  "cajas": "1",
  "doce": "0",
  "unidad": "0",
  "vunit": "70.00",
  "total": "70",
  "cant": "12",
  "undmy": "12",
  "undmn": "1",
  "leymy": "UND",
  "leymn": "UND",
  "lote": "VT-04",
  "grat": "1",
  "locked": "No"
},
]