[
{
  "numero": "T001-00022176",
  "fecha": "26/05/2026",
  "ruc": "27671550",
  "nombre": "TOMAS PALACIOS JARA",
  "direccion": "CALLE VIA MARAÑON 335 STO. TOMAS CUTERVO CAJAMARCA",
  "moneda": "0",
  "totguia": "175",
  "acuenta": "175",
  "saldo": "0.0000",
  "tipc": "3.4",
  "estado": "0",
  "traslado": "0.0000",
  "obs": "",
  "codart": "5012W",
  "descripcion": "JARRO CONICO C/ BASE CUADRADA (CAJA X  4 DOC)",
  "cajas": "1",
  "doce": "0",
  "unidad": "0",
  "vunit": "175.00",
  "total": "175.00",
  "cant": "48",
  "undmy": "4",
  "undmn": "12",
  "leymy": "DOC",
  "leymn": "UND",
  "aux": "0",
  "cunit": "3.64583333333333",
  "cantimp": "1 CAJ",
  "vacio1": "",
  "vacio2": "",
  "auto": "SOFI",
  "preal": "175",
  "punidad": "0.0000"
},
]