[
{
  "numero": "T001-00017555",
  "fecha": "16/10/2025",
  "ruc": "20611791799",
  "nombre": "CORPORACION DON CALDERON SOCIEDAD ANONIMA CERRADA",
  "direccion": "AV. UNIVERSITARIA NORTE URB. SAN JUAN BAUTISTA N° 9359 INT. LT. DP. MZ. KM. LIMA LIMA COMAS",
  "moneda": "0",
  "totguia": "280",
  "acuenta": "280",
  "saldo": "0.0000",
  "tipc": "3.7",
  "estado": "0",
  "traslado": "0.0000",
  "obs": "",
  "codart": "YL24712",
  "descripcion": "FUENTE CERAMICA (CAJA X  30 UND)",
  "cajas": "1",
  "doce": "0",
  "unidad": "0",
  "vunit": "280.00",
  "total": "280.00",
  "cant": "30",
  "undmy": "30",
  "undmn": "1",
  "leymy": "UND",
  "leymn": "UND",
  "aux": "0",
  "cunit": "9.33333333333333",
  "cantimp": "1 CAJ",
  "vacio1": "",
  "vacio2": "",
  "auto": "-",
  "preal": "280",
  "punidad": "0.0000"
},
]