[
{
  "numero": "T001-00018236",
  "fecha": "19/11/2025",
  "ruc": "10048263912",
  "nombre": "QUISPE APAZA LUISA",
  "direccion": "BLOQUE JOSE OLAYA 08 MDO MADRE DE DIOS - TAMBOPATA - TAMBOP",
  "moneda": "0",
  "totguia": "807",
  "acuenta": "807",
  "saldo": "0.0000",
  "tipc": "3.7",
  "estado": "0",
  "traslado": "0.0000",
  "obs": "ARRO8D..429",
  "codart": "ARRO8DIS-SUNDA",
  "descripcion": "ARROCERO 8 FULL PRINT  (CAJA X  60 UND)",
  "cajas": "1",
  "doce": "0",
  "unidad": "0",
  "vunit": "124.00",
  "total": "124.00",
  "cant": "60",
  "undmy": "60",
  "undmn": "1",
  "leymy": "UND",
  "leymn": "UND",
  "aux": "0",
  "cunit": "2.06666666666667",
  "cantimp": "1 CAJ",
  "vacio1": "",
  "vacio2": "",
  "auto": "-",
  "preal": "124",
  "punidad": "0.0000"
},
{
  "codart": "JBOLA",
  "descripcion": "JARRO BOLA DECORADO \"GALLERY\" (CAJA X  4 DOC)",
  "cajas": "1",
  "doce": "0",
  "unidad": "0",
  "vunit": "100.00",
  "total": "100.00",
  "cant": "48",
  "undmy": "4",
  "undmn": "12",
  "leymy": "DOC",
  "leymn": "UND",
  "aux": "0",
  "cunit": "2.08333333333333",
  "cantimp": "1 CAJ",
  "vacio1": "",
  "vacio2": "",
  "auto": "SOFI",
  "preal": "105",
  "punidad": "0.0000"
},
{
  "codart": "J-CARITAS",
  "descripcion": "JARRO 11 OZ CARITAS COLORES (CAJA X  4 DOC)",
  "cajas": "1",
  "doce": "0",
  "unidad": "0",
  "vunit": "132.00",
  "total": "132.00",
  "cant": "48",
  "undmy": "4",
  "undmn": "12",
  "leymy": "DOC",
  "leymn": "UND",
  "aux": "0",
  "cunit": "2.75",
  "cantimp": "1 CAJ",
  "vacio1": "",
  "vacio2": "",
  "auto": "-",
  "preal": "132",
  "punidad": "0.0000"
},
{
  "codart": "JRECTO-MORELLA",
  "descripcion": "JARRO 11 OZ RECTO DECORADO MORELLA  (CAJA X  4 DOC)",
  "cajas": "1",
  "doce": "0",
  "unidad": "0",
  "vunit": "88.00",
  "total": "88.00",
  "cant": "48",
  "undmy": "4",
  "undmn": "12",
  "leymy": "DOC",
  "leymn": "UND",
  "aux": "0",
  "cunit": "1.83333333333333",
  "cantimp": "1 CAJ",
  "vacio1": "",
  "vacio2": "",
  "auto": "-",
  "preal": "88",
  "punidad": "0.0000"
},
{
  "codart": "PA35",
  "descripcion": "PLATO 10.5\" RUSTICO STD-A35  (CAJA X  26 UND)",
  "cajas": "1",
  "doce": "0",
  "unidad": "0",
  "vunit": "99.00",
  "total": "99.00",
  "cant": "26",
  "undmy": "26",
  "undmn": "1",
  "leymy": "UND",
  "leymn": "UND",
  "aux": "0",
  "cunit": "3.80769230769231",
  "cantimp": "1 CAJ",
  "vacio1": "",
  "vacio2": "",
  "auto": "-",
  "preal": "99",
  "punidad": "0.0000"
},
{
  "codart": "TCW-153",
  "descripcion": "PLATO 10.5\" COLOR NEGRO  (CAJA X  30 UND)",
  "cajas": "1",
  "doce": "0",
  "unidad": "0",
  "vunit": "150.00",
  "total": "150.00",
  "cant": "30",
  "undmy": "30",
  "undmn": "1",
  "leymy": "UND",
  "leymn": "UND",
  "aux": "0",
  "cunit": "5",
  "cantimp": "1 CAJ",
  "vacio1": "",
  "vacio2": "",
  "auto": "-",
  "preal": "150",
  "punidad": "0.0000"
},
{
  "codart": "TCW-196",
  "descripcion": "PLATO 10.5\" RUSTICO (CAJA X  30 UND)",
  "cajas": "1",
  "doce": "0",
  "unidad": "0",
  "vunit": "114.00",
  "total": "114.00",
  "cant": "30",
  "undmy": "30",
  "undmn": "1",
  "leymy": "UND",
  "leymn": "UND",
  "aux": "0",
  "cunit": "3.8",
  "cantimp": "1 CAJ",
  "vacio1": "",
  "vacio2": "",
  "auto": "-",
  "preal": "114",
  "punidad": "0.0000"
},
]