[
{
  "numero": "T001-00016183",
  "fecha": "22/07/2025",
  "ruc": "10214710558",
  "nombre": "HUAMAN BAUTISTA GLORIA MARINA",
  "direccion": "CAL.LA MAR N#133(MEDIA CDRA IGLESIA JESUS MARIA)ICA-ICA-ICA",
  "moneda": "0",
  "totguia": "2013",
  "acuenta": "2013",
  "saldo": "0.0000",
  "tipc": "3.7",
  "estado": "0",
  "traslado": "0.0000",
  "obs": "",
  "codart": "ARRO8W-BGP-8",
  "descripcion": "PLATO 8\" ARROCERO BLANCO (CAJA X  60 UND)",
  "cajas": "1",
  "doce": "0",
  "unidad": "0",
  "vunit": "115.00",
  "total": "115.00",
  "cant": "60",
  "undmy": "60",
  "undmn": "1",
  "leymy": "UND",
  "leymn": "UND",
  "aux": "0",
  "cunit": "1.91666666666667",
  "cantimp": "1 CAJ",
  "vacio1": "",
  "vacio2": "",
  "auto": "-",
  "preal": "115",
  "punidad": "0.0000"
},
{
  "codart": "ARRO9W-BGP-9",
  "descripcion": "PLATO 9\" ARROCERO BLANCO (CAJA X  40 UND)",
  "cajas": "1",
  "doce": "0",
  "unidad": "0",
  "vunit": "100.00",
  "total": "100.00",
  "cant": "40",
  "undmy": "40",
  "undmn": "1",
  "leymy": "UND",
  "leymn": "UND",
  "aux": "0",
  "cunit": "2.5",
  "cantimp": "1 CAJ",
  "vacio1": "",
  "vacio2": "",
  "auto": "-",
  "preal": "100",
  "punidad": "0.0000"
},
{
  "codart": "PLT10.5CW-SUNDA",
  "descripcion": "PLATO 10.5 CUADRADO BLANCO SUNDA (CAJA X  3 DOC)",
  "cajas": "2",
  "doce": "0",
  "unidad": "0",
  "vunit": "145.00",
  "total": "290.00",
  "cant": "72",
  "undmy": "3",
  "undmn": "12",
  "leymy": "DOC",
  "leymn": "UND",
  "aux": "0",
  "cunit": "4.02777777777778",
  "cantimp": "2 CAJ",
  "vacio1": "",
  "vacio2": "",
  "auto": "-",
  "preal": "135",
  "punidad": "0.0000"
},
{
  "codart": "PLT7.5RD-GALLERY",
  "descripcion": "PLATO 7.5\" BEBE M/GALLERY (CAJA X  6 DOC)",
  "cajas": "2",
  "doce": "0",
  "unidad": "0",
  "vunit": "158.00",
  "total": "316.00",
  "cant": "144",
  "undmy": "6",
  "undmn": "12",
  "leymy": "DOC",
  "leymn": "UND",
  "aux": "0",
  "cunit": "2.19444444444444",
  "cantimp": "2 CAJ",
  "vacio1": "",
  "vacio2": "",
  "auto": "-",
  "preal": "158",
  "punidad": "0.0000"
},
{
  "codart": "PLT9D HONDO",
  "descripcion": "PLATO 9\" HONDO DECORADO GALLERY (CAJA X  6 DOC)",
  "cajas": "1",
  "doce": "0",
  "unidad": "0",
  "vunit": "160.00",
  "total": "160.00",
  "cant": "72",
  "undmy": "6",
  "undmn": "12",
  "leymy": "DOC",
  "leymn": "UND",
  "aux": "0",
  "cunit": "2.22222222222222",
  "cantimp": "1 CAJ",
  "vacio1": "",
  "vacio2": "",
  "auto": "SOFI",
  "preal": "165",
  "punidad": "0.0000"
},
{
  "codart": "PLT9DH-SUNDA",
  "descripcion": "PLATO 9\" HONDO LISO SUNDA (CAJA X  72 UND)",
  "cajas": "4",
  "doce": "0",
  "unidad": "0",
  "vunit": "160.00",
  "total": "640.00",
  "cant": "288",
  "undmy": "72",
  "undmn": "1",
  "leymy": "UND",
  "leymn": "UND",
  "aux": "0",
  "cunit": "2.22222222222222",
  "cantimp": "4 CAJ",
  "vacio1": "",
  "vacio2": "",
  "auto": "-",
  "preal": "160",
  "punidad": "0.0000"
},
{
  "codart": "SOP8D-GALLERY",
  "descripcion": "SOPERO 8\" C/DISEÑO \"GALLERY\" (CAJA X  4 DOC)",
  "cajas": "2",
  "doce": "0",
  "unidad": "0",
  "vunit": "126.00",
  "total": "252.00",
  "cant": "96",
  "undmy": "4",
  "undmn": "12",
  "leymy": "DOC",
  "leymn": "UND",
  "aux": "0",
  "cunit": "2.625",
  "cantimp": "2 CAJ",
  "vacio1": "",
  "vacio2": "",
  "auto": "-",
  "preal": "126",
  "punidad": "0.0000"
},
{
  "codart": "SR001",
  "descripcion": "BOLO 6\" NEGRO CUADRADO (CAJA X  36 UND)",
  "cajas": "1",
  "doce": "0",
  "unidad": "0",
  "vunit": "140.00",
  "total": "140.00",
  "cant": "36",
  "undmy": "36",
  "undmn": "1",
  "leymy": "UND",
  "leymn": "UND",
  "aux": "0",
  "cunit": "3.88888888888889",
  "cantimp": "1 CAJ",
  "vacio1": "",
  "vacio2": "",
  "auto": "-",
  "preal": "140",
  "punidad": "0.0000"
},
]