[
{
  "numero": "T001-00017549",
  "fecha": "16/10/2025",
  "ruc": "20613550357",
  "nombre": "INVERSIONES JOTA CRUZ E.I.R.L.",
  "direccion": "CAL. 10 A.V. RIO SANTA N° INT. LT. 9 DP. MZ. K KM. LIMA LIMA LOS OLIVOS",
  "moneda": "0",
  "totguia": "668",
  "acuenta": "668",
  "saldo": "0.0000",
  "tipc": "3.7",
  "estado": "0",
  "traslado": "0.0000",
  "obs": "",
  "codart": "2020-1X12",
  "descripcion": "BOLO DE CERAMICA X3 GRANDE (CAJA X  1 DOC)",
  "cajas": "1",
  "doce": "0",
  "unidad": "0",
  "vunit": "250.00",
  "total": "250.00",
  "cant": "12",
  "undmy": "1",
  "undmn": "12",
  "leymy": "DOC",
  "leymn": "UND",
  "aux": "0",
  "cunit": "20.8333333333333",
  "cantimp": "1 CAJ",
  "vacio1": "",
  "vacio2": "",
  "auto": "-",
  "preal": "250",
  "punidad": "0.0000"
},
{
  "codart": "BLW-5",
  "descripcion": "TAPER X 5PCS DE VIDRIO C/TAPA (CAJA X  12 SET)",
  "cajas": "1",
  "doce": "0",
  "unidad": "0",
  "vunit": "90.00",
  "total": "90.00",
  "cant": "12",
  "undmy": "12",
  "undmn": "1",
  "leymy": "SET",
  "leymn": "UND",
  "aux": "0",
  "cunit": "7.5",
  "cantimp": "1 CAJ",
  "vacio1": "",
  "vacio2": "",
  "auto": "-",
  "preal": "90",
  "punidad": "0.0000"
},
{
  "codart": "DT470-BMDP01",
  "descripcion": "TAZA DE VIDRIO 470ML X 3 G-HORSE (CAJA X  12 SET)",
  "cajas": "1",
  "doce": "0",
  "unidad": "0",
  "vunit": "108.00",
  "total": "108.00",
  "cant": "12",
  "undmy": "12",
  "undmn": "1",
  "leymy": "SET",
  "leymn": "UND",
  "aux": "0",
  "cunit": "9",
  "cantimp": "1 CAJ",
  "vacio1": "",
  "vacio2": "",
  "auto": "-",
  "preal": "108",
  "punidad": "0.0000"
},
{
  "codart": "PLT8CW-SUNDA",
  "descripcion": "PLATO 8\" CUADRADO BLANCO (CAJA X  72 UND)",
  "cajas": "1",
  "doce": "0",
  "unidad": "0",
  "vunit": "135.00",
  "total": "135.00",
  "cant": "72",
  "undmy": "72",
  "undmn": "1",
  "leymy": "UND",
  "leymn": "UND",
  "aux": "0",
  "cunit": "1.875",
  "cantimp": "1 CAJ",
  "vacio1": "",
  "vacio2": "",
  "auto": "-",
  "preal": "135",
  "punidad": "0.0000"
},
{
  "codart": "SM4000800",
  "descripcion": "PLATO 9\" HONDO ASTRAL DURALEX (CAJA X  24 UND)",
  "cajas": "1",
  "doce": "0",
  "unidad": "0",
  "vunit": "85.00",
  "total": "85.00",
  "cant": "24",
  "undmy": "24",
  "undmn": "1",
  "leymy": "UND",
  "leymn": "UND",
  "aux": "0",
  "cunit": "3.54166666666667",
  "cantimp": "1 CAJ",
  "vacio1": "",
  "vacio2": "",
  "auto": "-",
  "preal": "85",
  "punidad": "0.0000"
},
]