[
{
  "numero": "T001-00020675",
  "fecha": "11/03/2026",
  "ruc": "20615469361",
  "nombre": "FIBAY CORP SAC",
  "direccion": "AV. VICTORIA DE COPACABANA LT.63-MZ B-LIMA-PUENTE PIEDRA ",
  "moneda": "0",
  "totguia": "594",
  "acuenta": "594",
  "saldo": "0.0000",
  "tipc": "3.4",
  "estado": "0",
  "traslado": "0.0000",
  "obs": "",
  "codart": "0045AL",
  "descripcion": "VASO LEXINGTON ROCKS (CAJA X 4 DOC)",
  "cajas": "3",
  "doce": "0",
  "unidad": "0",
  "vunit": "93.00",
  "total": "279.00",
  "cant": "144",
  "undmy": "4",
  "undmn": "12",
  "leymy": "DOC",
  "leymn": "UND",
  "aux": "0",
  "cunit": "1.9375",
  "cantimp": "3 CAJ",
  "vacio1": "",
  "vacio2": "",
  "auto": "-",
  "preal": "93",
  "punidad": "0.0000"
},
{
  "codart": "0046AL",
  "descripcion": "VASO LEXINGTON AGUA CRISTAR (CAJA X 4 DOC)",
  "cajas": "3",
  "doce": "0",
  "unidad": "0",
  "vunit": "105.00",
  "total": "315.00",
  "cant": "144",
  "undmy": "4",
  "undmn": "12",
  "leymy": "DOC",
  "leymn": "UND",
  "aux": "0",
  "cunit": "2.1875",
  "cantimp": "3 CAJ",
  "vacio1": "",
  "vacio2": "",
  "auto": "-",
  "preal": "105",
  "punidad": "0.0000"
},
]