[
{
  "numero": "-",
  "fecha": "01/12/2023",
  "ruc": "10067790907",
  "nombre": "AVILEZ GUTIERREZ ULISES",
  "direccion": "AV. ARRIBA PERU 735S/N CUSCO - LA CONVENCION - PICHARI",
  "moneda": "0",
  "totguia": "1622.2",
  "acuenta": "1622.2",
  "saldo": "0.0000",
  "tipc": "3.81",
  "estado": "0",
  "traslado": "0.0000",
  "obs": "",
  "codart": "4256",
  "descripcion": "PLATO BANDEJA (CAJA X  30 UND)",
  "cajas": "1",
  "doce": "0",
  "unidad": "0",
  "vunit": "298.00",
  "total": "298.00",
  "cant": "30",
  "undmy": "30",
  "undmn": "1",
  "leymy": "UND",
  "leymn": "UND",
  "aux": "0",
  "cunit": "9.93333333333333",
  "cantimp": "1 CAJ",
  "vacio1": "",
  "vacio2": "",
  "auto": "SOFI",
  "preal": "305.2",
  "punidad": "0.0000"
},
{
  "codart": "BD-29",
  "descripcion": "TAZA C/PLATO DECORADA (CAJA X  8 SET)",
  "cajas": "1",
  "doce": "0",
  "unidad": "0",
  "vunit": "179.00",
  "total": "179.00",
  "cant": "8",
  "undmy": "8",
  "undmn": "1",
  "leymy": "SET",
  "leymn": "UND",
  "aux": "0",
  "cunit": "22.375",
  "cantimp": "1 CAJ",
  "vacio1": "",
  "vacio2": "",
  "auto": "SOFI",
  "preal": "179.2",
  "punidad": "0.0000"
},
{
  "codart": "COCOX5",
  "descripcion": "VASO DE VIDRIO COCO (CAJA X  5 DOC)",
  "cajas": "4",
  "doce": "0",
  "unidad": "0",
  "vunit": "94.00",
  "total": "376.00",
  "cant": "240",
  "undmy": "5",
  "undmn": "12",
  "leymy": "DOC",
  "leymn": "UND",
  "aux": "0",
  "cunit": "1.56666666666667",
  "cantimp": "4 CAJ",
  "vacio1": "",
  "vacio2": "",
  "auto": "-",
  "preal": "94",
  "punidad": "0.0000"
},
{
  "codart": "LXNX001",
  "descripcion": "COPA P/HELADO DE VIDRIO 12.5 OZ (CAJA X  48 UND)",
  "cajas": "1",
  "doce": "0",
  "unidad": "0",
  "vunit": "158.40",
  "total": "158.40",
  "cant": "48",
  "undmy": "48",
  "undmn": "1",
  "leymy": "UND",
  "leymn": "UND",
  "aux": "0",
  "cunit": "3.3",
  "cantimp": "1 CAJ",
  "vacio1": "",
  "vacio2": "",
  "auto": "-",
  "preal": "158.4",
  "punidad": "0.0000"
},
{
  "codart": "LXZB30",
  "descripcion": "TAZA DE VIDRIO 13 OZ (CAJA X  48 UND)",
  "cajas": "1",
  "doce": "0",
  "unidad": "0",
  "vunit": "120.20",
  "total": "120.20",
  "cant": "48",
  "undmy": "48",
  "undmn": "1",
  "leymy": "UND",
  "leymn": "UND",
  "aux": "0",
  "cunit": "2.50416666666667",
  "cantimp": "1 CAJ",
  "vacio1": "",
  "vacio2": "",
  "auto": "-",
  "preal": "120.2",
  "punidad": "0.0000"
},
{
  "codart": "NC-8574",
  "descripcion": "FLORERO DE VIDRIO AMARILLO (CAJA X  4 SET)",
  "cajas": "1",
  "doce": "0",
  "unidad": "0",
  "vunit": "80.60",
  "total": "80.60",
  "cant": "4",
  "undmy": "4",
  "undmn": "1",
  "leymy": "SET",
  "leymn": "UND",
  "aux": "0",
  "cunit": "20.15",
  "cantimp": "1 CAJ",
  "vacio1": "",
  "vacio2": "",
  "auto": "-",
  "preal": "80.6",
  "punidad": "0.0000"
},
{
  "codart": "VL-APPLE10",
  "descripcion": "OLLAS (CAJA X  2 SET) ",
  "cajas": "1",
  "doce": "0",
  "unidad": "0",
  "vunit": "410.00",
  "total": "410.00",
  "cant": "2",
  "undmy": "2",
  "undmn": "1",
  "leymy": "UND",
  "leymn": "UND",
  "aux": "0",
  "cunit": "205",
  "cantimp": "1 CAJ",
  "vacio1": "",
  "vacio2": "",
  "auto": "-",
  "preal": "410",
  "punidad": "0.0000"
},
]