[
{
  "dia": "Mié.",
  "fecha": "25/02/2026",
  "fechacab": "Feb. 25"
},
{
  "dia": "Jue.",
  "fecha": "26/02/2026",
  "fechacab": "Feb. 26"
},
{
  "dia": "Vie.",
  "fecha": "27/02/2026",
  "fechacab": "Feb. 27"
},
{
  "dia": "Sáb.",
  "fecha": "28/02/2026",
  "fechacab": "Feb. 28"
},
{
  "dia": "Lun.",
  "fecha": "02/03/2026",
  "fechacab": "Mar. 2"
},
{
  "dia": "Mar.",
  "fecha": "03/03/2026",
  "fechacab": "Mar. 3"
},
{
  "dia": "Mié.",
  "fecha": "04/03/2026",
  "fechacab": "Mar. 4"
},
{
  "dia": "Jue.",
  "fecha": "05/03/2026",
  "fechacab": "Mar. 5"
},
{
  "dia": "Vie.",
  "fecha": "06/03/2026",
  "fechacab": "Mar. 6"
},
{
  "dia": "Sáb.",
  "fecha": "07/03/2026",
  "fechacab": "Mar. 7"
},
{
  "dia": "Lun.",
  "fecha": "09/03/2026",
  "fechacab": "Mar. 9"
},
{
  "dia": "Mar.",
  "fecha": "10/03/2026",
  "fechacab": "Mar. 10"
},
{
  "dia": "Mié.",
  "fecha": "11/03/2026",
  "fechacab": "Mar. 11"
},
{
  "dia": "Jue.",
  "fecha": "12/03/2026",
  "fechacab": "Mar. 12"
},
{
  "dia": "Vie.",
  "fecha": "13/03/2026",
  "fechacab": "Mar. 13"
},
{
  "dia": "Sáb.",
  "fecha": "14/03/2026",
  "fechacab": "Mar. 14"
},
{
  "dia": "Lun.",
  "fecha": "16/03/2026",
  "fechacab": "Mar. 16"
},
{
  "dia": "Mar.",
  "fecha": "17/03/2026",
  "fechacab": "Mar. 17"
},
{
  "dia": "Mié.",
  "fecha": "18/03/2026",
  "fechacab": "Mar. 18"
},
{
  "dia": "Jue.",
  "fecha": "19/03/2026",
  "fechacab": "Mar. 19"
},
{
  "dia": "Vie.",
  "fecha": "20/03/2026",
  "fechacab": "Mar. 20"
},
{
  "dia": "Sáb.",
  "fecha": "21/03/2026",
  "fechacab": "Mar. 21"
},
{
  "dia": "Lun.",
  "fecha": "23/03/2026",
  "fechacab": "Mar. 23"
},
{
  "dia": "Mar.",
  "fecha": "24/03/2026",
  "fechacab": "Mar. 24"
},
{
  "dia": "Mié.",
  "fecha": "25/03/2026",
  "fechacab": "Mar. 25"
},
{
  "dia": "Jue.",
  "fecha": "26/03/2026",
  "fechacab": "Mar. 26"
},
{
  "dia": "Hoy",
  "fecha": "27/03/2026",
  "fechacab": "Mar. 27"
},
]