[
{
  "numero": "COT-MOQ000700",
  "fecha": "18/05/2023",
  "ruc": "00000000002",
  "nombre": "MOQUEQUE",
  "moneda": "0",
  "totcompra": "404",
  "acuenta": "404",
  "saldo": "0.0000",
  "tipc": "3.82",
  "obs": "",
  "tipo": "NAC",
  "factura": "",
  "user": "MARTIN",
  "codart": "ARRO8_MEDA-SUNDA",
  "descripcion": "PLATO 8\" ARROCERO MEDALLON SUNDA (CAJA X  60 UND)",
  "cajas": "1",
  "doce": "0",
  "unidad": "0",
  "vunit": "144.00",
  "total": "144",
  "cant": "60",
  "undmy": "60",
  "undmn": "1",
  "leymy": "UND",
  "leymn": "UND",
  "lote": "ARRO8_MEDA-SUNDA",
  "grat": "1",
  "locked": "No"
},
{
  "codart": "SOP8_MEDA-GALLERY",
  "descripcion": "SOPERO 8\" C/DISEÑO MEDALLON GALLERY (CAJA X  50 UND)",
  "cajas": "2",
  "doce": "0",
  "unidad": "0",
  "vunit": "130.00",
  "total": "260",
  "cant": "100",
  "undmy": "50",
  "undmn": "1",
  "leymy": "UND",
  "leymn": "UND",
  "lote": "SOP8_MEDA-GALLERY",
  "grat": "1",
  "locked": "No"
},
]