[
{
  "numero": "COT-AGC0001-02926",
  "fecha": "13/12/2023",
  "ruc": "00000000035",
  "nombre": "AGC",
  "moneda": "0",
  "totcompra": "490",
  "acuenta": "490",
  "saldo": "0.0000",
  "tipc": "3.78",
  "obs": "",
  "tipo": "NAC",
  "factura": "",
  "user": "MARTIN",
  "codart": "TP350W_GALLERY",
  "descripcion": "TAZA C/ PLATO BLANCO GALLERY (CAJA X  8 SET)",
  "cajas": "2",
  "doce": "0",
  "unidad": "0",
  "vunit": "185.00",
  "total": "370",
  "cant": "16",
  "undmy": "8",
  "undmn": "1",
  "leymy": "SET",
  "leymn": "UND",
  "lote": "TP350W_GALLERY",
  "grat": "1",
  "locked": "No"
},
{
  "codart": "VT0200(X12)",
  "descripcion": "LONCHERA 1.25 LT. PORTALUNCH PERSONAL (CAJA X  12 UND)",
  "cajas": "0",
  "doce": "6",
  "unidad": "0",
  "vunit": "240.00",
  "total": "120",
  "cant": "6",
  "undmy": "12",
  "undmn": "1",
  "leymy": "UND",
  "leymn": "UND",
  "lote": "VT0200(X12)",
  "grat": "1",
  "locked": "No"
},
]