[
{
  "numero": "COT-CG005814",
  "fecha": "12/07/2023",
  "ruc": "20505694202",
  "nombre": "CENTER GLASS E.I.R.L",
  "moneda": "0",
  "totcompra": "141",
  "acuenta": "141",
  "saldo": "0.0000",
  "tipc": "3.65",
  "obs": "",
  "tipo": "NAC",
  "factura": "",
  "user": "MARTIN",
  "codart": "0355AL",
  "descripcion": "COPA AV LISA AGUARDIENTE .LORD  (CAJA X 6 DOC)",
  "cajas": "1",
  "doce": "0",
  "unidad": "0",
  "vunit": "141.00",
  "total": "141",
  "cant": "72",
  "undmy": "6",
  "undmn": "12",
  "leymy": "DOC",
  "leymn": "UND",
  "lote": "0355AL",
  "grat": "1",
  "locked": "No"
},
]