[
{
  "numero": "COT-MOQ000484",
  "fecha": "07/07/2023",
  "ruc": "00000000002",
  "nombre": "MOQUEQUE",
  "moneda": "0",
  "totcompra": "200",
  "acuenta": "200",
  "saldo": "0.0000",
  "tipc": "3.65",
  "obs": "",
  "tipo": "NAC",
  "factura": "",
  "user": "MARTIN",
  "codart": "3401-MOQ",
  "descripcion": "JARRO DECORADO (CAJA X  4 DOC)",
  "cajas": "1",
  "doce": "0",
  "unidad": "0",
  "vunit": "200.00",
  "total": "200",
  "cant": "48",
  "undmy": "4",
  "undmn": "12",
  "leymy": "DOC",
  "leymn": "UND",
  "lote": "3401-MOQ",
  "grat": "1",
  "locked": "No"
},
]