[
{
  "numero": "COT-28102023",
  "fecha": "28/10/2023",
  "ruc": "00000000000",
  "nombre": "CLIENTES VARIOS",
  "moneda": "0",
  "totcompra": "1500",
  "acuenta": "1500",
  "saldo": "0.0000",
  "tipc": "3.87",
  "obs": "ZULEICA",
  "tipo": "NAC",
  "factura": "",
  "user": "DANTE",
  "codart": "5440AC",
  "descripcion": "COPA ROJA CHAMPAÑA  (CAJA X  12 UND)",
  "cajas": "30",
  "doce": "0",
  "unidad": "0",
  "vunit": "50.00",
  "total": "1500",
  "cant": "360",
  "undmy": "12",
  "undmn": "1",
  "leymy": "UND",
  "leymn": "UND",
  "lote": "ZULEICA",
  "grat": "1",
  "locked": "No"
},
]