[
{
  "numero": "COT-P002607",
  "fecha": "21/12/2023",
  "ruc": "20505694202",
  "nombre": "CENTER GLASS E.I.R.L",
  "moneda": "0",
  "totcompra": "186",
  "acuenta": "186",
  "saldo": "0.0000",
  "tipc": "3.78",
  "obs": "",
  "tipo": "NAC",
  "factura": "",
  "user": "MARTIN",
  "codart": "0367AL",
  "descripcion": "JARRO AV LISO LONDON (CAJA X  36 UND)",
  "cajas": "2",
  "doce": "0",
  "unidad": "0",
  "vunit": "93.00",
  "total": "186",
  "cant": "72",
  "undmy": "36",
  "undmn": "1",
  "leymy": "UND",
  "leymn": "UND",
  "lote": "0367AL",
  "grat": "1",
  "locked": "No"
},
]