[
{
  "numero": "COT-09052024-049",
  "fecha": "09/05/2024",
  "ruc": "20538347281",
  "nombre": "INVERSIONES DIAMANTE PERU S.A.C.",
  "moneda": "1",
  "totcompra": "440",
  "acuenta": "440",
  "saldo": "0.0000",
  "tipc": "3.72",
  "obs": "",
  "tipo": "NAC",
  "factura": "",
  "user": "DANTE",
  "codart": "GB1804",
  "descripcion": "BOMBONERA DE VIDRIO (CAJA X  16 UND)",
  "cajas": "20",
  "doce": "0",
  "unidad": "0",
  "vunit": "22.00",
  "total": "440",
  "cant": "320",
  "undmy": "16",
  "undmn": "1",
  "leymy": "UND",
  "leymn": "UND",
  "lote": "GB1804",
  "grat": "1",
  "locked": "No"
},
]