[
{
  "numero": "COT-063370",
  "fecha": "11/07/2024",
  "ruc": "00000000048",
  "nombre": "RONGQUIAN",
  "moneda": "0",
  "totcompra": "3145",
  "acuenta": "3145",
  "saldo": "0.0000",
  "tipc": "3.797",
  "obs": "",
  "tipo": "NAC",
  "factura": "",
  "user": "DANTE",
  "codart": "WAN-103",
  "descripcion": "PLATO 10.5\" COLOR AZULINO (CAJA X  30 UND)",
  "cajas": "5",
  "doce": "0",
  "unidad": "0",
  "vunit": "81.00",
  "total": "405",
  "cant": "150",
  "undmy": "30",
  "undmn": "1",
  "leymy": "UND",
  "leymn": "UND",
  "lote": "WAN-103",
  "grat": "1",
  "locked": "No"
},
{
  "codart": "WAN-105",
  "descripcion": "PLATO 10.5\" COLOR (CAJA X  24 UND)",
  "cajas": "5",
  "doce": "0",
  "unidad": "0",
  "vunit": "67.00",
  "total": "335",
  "cant": "120",
  "undmy": "24",
  "undmn": "1",
  "leymy": "UND",
  "leymn": "UND",
  "lote": "WAN-105",
  "grat": "1",
  "locked": "No"
},
{
  "codart": "WAN-108",
  "descripcion": "PLATO 10.5\" COLOR (CAJA X  30 UND)",
  "cajas": "5",
  "doce": "0",
  "unidad": "0",
  "vunit": "78.00",
  "total": "390",
  "cant": "150",
  "undmy": "30",
  "undmn": "1",
  "leymy": "UND",
  "leymn": "UND",
  "lote": "WAN-108",
  "grat": "1",
  "locked": "No"
},
{
  "codart": "WAN-109",
  "descripcion": "PLATO 10.5\" COLOR (CAJA X  24 UND)",
  "cajas": "5",
  "doce": "0",
  "unidad": "0",
  "vunit": "65.00",
  "total": "325",
  "cant": "120",
  "undmy": "24",
  "undmn": "1",
  "leymy": "UND",
  "leymn": "UND",
  "lote": "WAN-109",
  "grat": "1",
  "locked": "No"
},
{
  "codart": "WAN-110",
  "descripcion": "PLATO 10.5\" COLOR (CAJA X  30 UND)",
  "cajas": "5",
  "doce": "0",
  "unidad": "0",
  "vunit": "81.00",
  "total": "405",
  "cant": "150",
  "undmy": "30",
  "undmn": "1",
  "leymy": "UND",
  "leymn": "UND",
  "lote": "WAN-110",
  "grat": "1",
  "locked": "No"
},
{
  "codart": "WAN-111",
  "descripcion": "PLATO 10.5\" COLOR (CAJA X  24 UND)",
  "cajas": "5",
  "doce": "0",
  "unidad": "0",
  "vunit": "65.00",
  "total": "325",
  "cant": "120",
  "undmy": "24",
  "undmn": "1",
  "leymy": "UND",
  "leymn": "UND",
  "lote": "WAN-111",
  "grat": "1",
  "locked": "No"
},
{
  "codart": "WAN-117",
  "descripcion": "PLATO 10.5\" CUADRADO NEGRO (CAJA X  30 UND)",
  "cajas": "10",
  "doce": "0",
  "unidad": "0",
  "vunit": "96.00",
  "total": "960",
  "cant": "300",
  "undmy": "30",
  "undmn": "1",
  "leymy": "UND",
  "leymn": "UND",
  "lote": "WAN-117",
  "grat": "1",
  "locked": "No"
},
]