[
{
  "numero": "COT-000590",
  "fecha": "17/01/2024",
  "ruc": "00000000000",
  "nombre": "CLIENTES VARIOS",
  "moneda": "0",
  "totcompra": "1350",
  "acuenta": "1350",
  "saldo": "0.0000",
  "tipc": "3.73",
  "obs": "",
  "tipo": "NAC",
  "factura": "",
  "user": "MARTIN",
  "codart": "V-169-2",
  "descripcion": "VASOS (CAJA X  20 SET)",
  "cajas": "10",
  "doce": "0",
  "unidad": "0",
  "vunit": "135.00",
  "total": "1350",
  "cant": "200",
  "undmy": "20",
  "undmn": "1",
  "leymy": "SET",
  "leymn": "UND",
  "lote": "V-169-2",
  "grat": "1",
  "locked": "No"
},
]