[
{
  "numero": "COT-DIA24001403",
  "fecha": "23/05/2024",
  "ruc": "20538347281",
  "nombre": "INVERSIONES DIAMANTE PERU S.A.C.",
  "moneda": "1",
  "totcompra": "3251.8",
  "acuenta": "3251.8",
  "saldo": "0.0000",
  "tipc": "3.74",
  "obs": "",
  "tipo": "NAC",
  "factura": "",
  "user": "DANTE",
  "codart": "SR5277",
  "descripcion": "BOLO 6\" (BOL6BW) BLANCO C/BORDE (CAJA X  64 UND)",
  "cajas": "15",
  "doce": "0",
  "unidad": "0",
  "vunit": "32.50",
  "total": "487.5",
  "cant": "960",
  "undmy": "64",
  "undmn": "1",
  "leymy": "UND",
  "leymn": "UND",
  "lote": "BOL6BW",
  "grat": "1",
  "locked": "No"
},
{
  "codart": "SR6506",
  "descripcion": "PLATON (PT11RN) TENDIDO NEGRO BLANCO (CAJA X  24 UND)",
  "cajas": "5",
  "doce": "0",
  "unidad": "0",
  "vunit": "26.80",
  "total": "134",
  "cant": "120",
  "undmy": "24",
  "undmn": "1",
  "leymy": "UND",
  "leymn": "UND",
  "lote": "PLT11RN",
  "grat": "1",
  "locked": "No"
},
{
  "codart": "SR7546",
  "descripcion": "BOLO 7\" (BOL7N) NEGRO  (CAJA X  48 UND)",
  "cajas": "15",
  "doce": "0",
  "unidad": "0",
  "vunit": "45.00",
  "total": "675",
  "cant": "720",
  "undmy": "48",
  "undmn": "1",
  "leymy": "UND",
  "leymn": "UND",
  "lote": "BOL7N",
  "grat": "1",
  "locked": "No"
},
{
  "codart": "SR6534",
  "descripcion": "PLATO 10.5\" (PT10.5RN) RUSTICO (CAJA X  36 UND)",
  "cajas": "15",
  "doce": "0",
  "unidad": "0",
  "vunit": "38.00",
  "total": "570",
  "cant": "540",
  "undmy": "36",
  "undmn": "1",
  "leymy": "UND",
  "leymn": "UND",
  "lote": "PLT10.5RN",
  "grat": "1",
  "locked": "No"
},
{
  "codart": "SR6516",
  "descripcion": "PLATON 11\" (PT11FN)  CUADRADO COLORES (CAJA X  24 UND)",
  "cajas": "25",
  "doce": "0",
  "unidad": "0",
  "vunit": "26.50",
  "total": "662.5",
  "cant": "600",
  "undmy": "24",
  "undmn": "1",
  "leymy": "UND",
  "leymn": "UND",
  "lote": "PLT10.5FN",
  "grat": "1",
  "locked": "No"
},
{
  "codart": "SR7287",
  "descripcion": "AJICERO 220CC (DJ220N) NEGRO (CAJA X  120 UND)",
  "cajas": "15",
  "doce": "0",
  "unidad": "0",
  "vunit": "30.52",
  "total": "457.8",
  "cant": "1800",
  "undmy": "120",
  "undmn": "1",
  "leymy": "UND",
  "leymn": "UND",
  "lote": "DJ220N",
  "grat": "1",
  "locked": "No"
},
{
  "codart": "SR7495",
  "descripcion": "PLATO 14\" (P14ON) OVALADO NEGRO C/PUNTOS  (CAJA X  36 UND)",
  "cajas": "5",
  "doce": "0",
  "unidad": "0",
  "vunit": "53.00",
  "total": "265",
  "cant": "180",
  "undmy": "36",
  "undmn": "1",
  "leymy": "UND",
  "leymn": "UND",
  "lote": "P14ON",
  "grat": "1",
  "locked": "No"
},
]