[
{
  "numero": "COT-DIA24000289",
  "fecha": "30/01/2024",
  "ruc": "20538347281",
  "nombre": "INVERSIONES DIAMANTE PERU S.A.C.",
  "moneda": "1",
  "totcompra": "1650",
  "acuenta": "1650",
  "saldo": "0.0000",
  "tipc": "3.81",
  "obs": "",
  "tipo": "NAC",
  "factura": "",
  "user": "DANTE",
  "codart": "PLT9D-LISOGALL",
  "descripcion": "PLATO 9\" DECORADO LISO \"GALLERY\" HYT  (CAJA X  6 DOC)",
  "cajas": "50",
  "doce": "0",
  "unidad": "0",
  "vunit": "33.00",
  "total": "1650",
  "cant": "3600",
  "undmy": "6",
  "undmn": "12",
  "leymy": "DOC",
  "leymn": "UND",
  "lote": "PLT9D-LISOGALL",
  "grat": "1",
  "locked": "No"
},
]