[
{
  "numero": "FAC-F063-00045263",
  "fecha": "03/02/2024",
  "ruc": "20100047137",
  "nombre": "UNION YCHICAWA S.A",
  "moneda": "1",
  "totcompra": "139.23",
  "acuenta": "139.23",
  "saldo": "0.0000",
  "tipc": "3.82",
  "obs": "",
  "tipo": "NAC",
  "factura": "",
  "user": "DANTE",
  "codart": "P00549",
  "descripcion": "PLATO 10\" TENDIDO C/BORDE  AZUL (CAJA X  18 UND)",
  "cajas": "7",
  "doce": "0",
  "unidad": "0",
  "vunit": "19.89",
  "total": "139.23",
  "cant": "126",
  "undmy": "18",
  "undmn": "1",
  "leymy": "UND",
  "leymn": "UND",
  "lote": "P00549",
  "grat": "1",
  "locked": "No"
},
]