[
{
  "numero": "FAC-F063-00047182",
  "fecha": "06/04/2024",
  "ruc": "20100047137",
  "nombre": "UNION YCHICAWA S.A",
  "moneda": "1",
  "totcompra": "20",
  "acuenta": "20",
  "saldo": "0.0000",
  "tipc": "3.75",
  "obs": "",
  "tipo": "NAC",
  "factura": "",
  "user": "MARTIN",
  "codart": "J172800-R",
  "descripcion": "JARRA MANCORA 2.8LT TAPA PLASTICA (CAJA X  6 UND)",
  "cajas": "1",
  "doce": "0",
  "unidad": "0",
  "vunit": "20.00",
  "total": "20",
  "cant": "6",
  "undmy": "6",
  "undmn": "1",
  "leymy": "UND",
  "leymn": "UND",
  "lote": "J172800-R",
  "grat": "1",
  "locked": "No"
},
]